{
    "DBCP-100": [
        "org.apache.commons.dbcp.datasources.SharedPoolDataSource"
    ],
    "DBCP-116": [
        "org.apache.commons.dbcp.datasources.CPDSConnectionFactory",
        "org.apache.commons.dbcp.datasources.InstanceKeyDataSource",
        "org.apache.commons.dbcp.datasources.KeyedCPDSConnectionFactory",
        "org.apache.commons.dbcp.datasources.PerUserPoolDataSource",
        "org.apache.commons.dbcp.datasources.SharedPoolDataSource"
    ],
    "DBCP-225": [
        "org.apache.commons.dbcp.PoolableConnectionFactory",
        "org.apache.commons.dbcp.datasources.CPDSConnectionFactory",
        "org.apache.commons.dbcp.datasources.KeyedCPDSConnectionFactory"
    ],
    "DBCP-235": [
        "org.apache.commons.dbcp.DelegatingConnection",
        "org.apache.commons.dbcp.managed.ManagedConnection",
        "org.apache.commons.dbcp.managed.TestManagedDataSource"
    ],
    "DBCP-237": [
        "org.apache.commons.dbcp.datasources.InstanceKeyDataSource",
        "org.apache.commons.dbcp.datasources.TestInstanceKeyDataSource"
    ],
    "DBCP-242": [
        "org.apache.commons.dbcp.DelegatingConnection"
    ],
    "DBCP-245": [
        "org.apache.commons.dbcp.datasources.SharedPoolDataSource",
        "org.apache.commons.dbcp.datasources.TestSharedPoolDataSource"
    ],
    "DBCP-264": [
        "org.apache.commons.dbcp.PoolablePreparedStatement"
    ],
    "DBCP-269": [
        "org.apache.commons.dbcp.DelegatingConnection",
        "org.apache.commons.dbcp.PoolableConnection"
    ],
    "DBCP-270": [
        "org.apache.commons.dbcp.AbandonedTrace"
    ],
    "DBCP-272": [
        "org.apache.commons.dbcp.BasicDataSource",
        "org.apache.commons.dbcp.cpdsadapter.DriverAdapterCPDS"
    ],
    "DBCP-284": [
        "org.apache.commons.dbcp.BasicDataSourceFactory"
    ],
    "DBCP-288": [
        "org.apache.commons.dbcp.DelegatingConnection"
    ],
    "DBCP-294": [
        "org.apache.commons.dbcp.BasicDataSource",
        "org.apache.commons.dbcp.PoolableConnectionFactory",
        "org.apache.commons.dbcp.managed.BasicManagedDataSource",
        "org.apache.commons.dbcp.managed.PoolableManagedConnection",
        "org.apache.commons.dbcp.managed.PoolableManagedConnectionFactory",
        "org.apache.commons.dbcp.managed.TransactionRegistry",
        "org.apache.commons.dbcp.managed.TestBasicManagedDataSource"
    ],
    "DBCP-303": [
        "org.apache.commons.dbcp.cpdsadapter.PooledConnectionImpl"
    ],
    "DBCP-355": [
        "org.apache.commons.dbcp.managed.DataSourceXAConnectionFactory",
        "org.apache.commons.dbcp.managed.TestDataSourceXAConnectionFactory",
        "org.apache.commons.dbcp.managed.TesterBasicXAConnection"
    ],
    "DBCP-358": [
        "org.apache.commons.dbcp2.DelegatingConnection",
        "org.apache.commons.dbcp2.DelegatingDatabaseMetaData",
        "org.apache.commons.dbcp2.DelegatingResultSet",
        "org.apache.commons.dbcp2.DelegatingStatement",
        "org.apache.commons.dbcp2.datasources.InstanceKeyObjectFactory",
        "org.apache.commons.dbcp2.managed.TransactionRegistry",
        "org.apache.commons.dbcp2.TestDelegatingCallableStatement",
        "org.apache.commons.dbcp2.TestDelegatingConnection",
        "org.apache.commons.dbcp2.TestDelegatingDatabaseMetaData",
        "org.apache.commons.dbcp2.TestDelegatingPreparedStatement",
        "org.apache.commons.dbcp2.TestDelegatingStatement",
        "org.apache.commons.dbcp2.TestPoolingDataSource",
        "org.apache.commons.dbcp2.datasources.TestSharedPoolDataSource",
        "org.apache.commons.dbcp2.managed.TestManagedDataSource",
        "org.apache.commons.dbcp2.managed.TestManagedDataSourceInTx"
    ],
    "DBCP-359": [
        "org.apache.commons.dbcp.DelegatingConnection",
        "org.apache.commons.dbcp.TestDelegatingConnection"
    ],
    "DBCP-403": [
        "org.apache.commons.dbcp2.DelegatingStatement"
    ],
    "DBCP-417": [
        "org.apache.commons.dbcp2.managed.TestManagedDataSource",
        "org.apache.commons.dbcp2.managed.TestManagedDataSourceInTx"
    ],
    "DBCP-428": [
        "org.apache.commons.dbcp2.managed.TransactionContext",
        "org.apache.commons.dbcp2.managed.TestTransactionContext"
    ],
    "DBCP-432": [
        "org.apache.commons.dbcp2.BasicDataSource",
        "org.apache.commons.dbcp2.TestBasicDataSource",
        "org.apache.commons.dbcp2.TesterConnRequestCountDriver",
        "org.apache.commons.dbcp2.TesterConnectionDelayDriver"
    ],
    "DBCP-433": [
        "org.apache.commons.dbcp2.managed.ManagedConnection",
        "org.apache.commons.dbcp2.managed.TestManagedConnection"
    ],
    "DBCP-434": [
        "org.apache.commons.dbcp2.BasicDataSource",
        "org.apache.commons.dbcp2.PoolableConnectionFactory",
        "org.apache.commons.dbcp2.managed.PoolableManagedConnectionFactory",
        "org.apache.commons.dbcp2.TestBasicDataSource",
        "org.apache.commons.dbcp2.TesterConnRequestCountDriver",
        "org.apache.commons.dbcp2.TesterConnectionDelayDriver"
    ],
    "DBCP-437": [
        "org.apache.commons.dbcp2.BasicDataSource",
        "org.apache.commons.dbcp2.managed.BasicManagedDataSource",
        "org.apache.commons.dbcp2.TestBasicDataSource",
        "org.apache.commons.dbcp2.TesterConnRequestCountDriver",
        "org.apache.commons.dbcp2.TesterConnectionDelayDriver"
    ],
    "DBCP-438": [
        "org.apache.commons.dbcp2.DelegatingConnection",
        "org.apache.commons.dbcp2.managed.TestManagedDataSource",
        "org.apache.commons.dbcp2.managed.TestManagedDataSourceInTx"
    ],
    "DBCP-446": [
        "org.apache.commons.dbcp2.DelegatingConnection",
        "org.apache.commons.dbcp2.TestDelegatingConnection"
    ],
    "DBCP-453": [
        "org.apache.commons.dbcp2.BasicDataSource",
        "org.apache.commons.dbcp2.TestBasicDataSourceFactory"
    ],
    "DBCP-457": [
        "org.apache.commons.dbcp2.BasicDataSource",
        "org.apache.commons.dbcp2.TestBasicDataSource",
        "org.apache.commons.dbcp2.TesterConnRequestCountDriver",
        "org.apache.commons.dbcp2.TesterConnectionDelayDriver"
    ],
    "DBCP-459": [
        "org.apache.commons.dbcp2.PoolingDataSource"
    ],
    "DBCP-472": [
        "org.apache.commons.dbcp2.PoolableConnection"
    ],
    "DBCP-484": [
        "org.apache.commons.dbcp2.managed.ManagedConnection"
    ],
    "DBCP-491": [
        "org.apache.commons.dbcp2.managed.ManagedConnection",
        "org.apache.commons.dbcp2.managed.TransactionContext",
        "org.apache.commons.dbcp2.managed.TransactionRegistry",
        "org.apache.commons.dbcp2.managed.TestConnectionWithNarayana"
    ],
    "DBCP-503": [
        "org.apache.commons.dbcp2.ListException",
        "org.apache.commons.dbcp2.datasources.InstanceKeyDataSourceFactory"
    ],
    "DBCP-516": [
        "org.apache.commons.dbcp2.managed.ManagedConnection",
        "org.apache.commons.dbcp2.managed.TestManagedDataSourceInTx"
    ],
    "DBCP-538": [
        "org.apache.commons.dbcp2.ObjectNameWrapper"
    ]
}